python_magic_file/__init__.py
python_magic_file/exceptions.py
python_magic_file/file.py
python_magic_file/utils.py
python_magic_file-0.0.7.dist-info/LICENSE
python_magic_file-0.0.7.dist-info/METADATA
python_magic_file-0.0.7.dist-info/WHEEL
python_magic_file-0.0.7.dist-info/top_level.txt
python_magic_file-0.0.7.dist-info/RECORD
