Metadata-Version: 2.1
Name: python-magic-file
Version: 0.0.7
Summary: Small Python module to aid developers in getting file extensions from files securely.
Home-page: https://github.com/vremes/python-magic-file
Author: Valtteri Remes
Classifier: Programming Language :: Python :: 3
Classifier: License :: OSI Approved :: MIT License
Requires-Python: >=3.6
License-File: LICENSE
Requires-Dist: python-magic (==0.4.27) ; platform_system != "Windows"
Requires-Dist: python-magic-bin (==0.4.14) ; platform_system == "Windows"
